[
    {
        "user_id":3,
        "activity":"SC",
        "week":1,
        "week_start_date":"2026-02-20",
        "total_peaks":37,
        "total_steps":37,
        "step_time_mean_sec":1.9415972549,
        "step_time_std_sec":0.5696013803,
        "step_time_cv_pct":29.1804660208,
        "total_duration_sec":33.9565005,
        "num_cycles":37,
        "cycle_time_mean_sec":1.8365066096,
        "cycle_time_std_sec":0.4132426129,
        "cycle_time_cv_pct":22.3513216348,
        "left_peaks":0,
        "right_peaks":0,
        "composite_score":68.8740062711,
        "user_group":"stable",
        "best_activity":"SC",
        "composite_score_norm":0.696592385,
        "step_time_cv_pct_norm":0.3023467736,
        "cycle_time_cv_pct_norm":0.1963686675,
        "total_duration_sec_norm":0.1535797903,
        "total_peaks_norm":0.1223628692,
        "composite_score_overall":49.5296233023,
        "perf_change_pct_SC":0.0,
        "perf_change_pct_STS":0.0,
        "perf_change_pct_TUG":0.0,
        "perf_change_pct_W":0.0,
        "perf_change_pct_overall":0.0,
        "percentile_rank_absolute":16.6666666667,
        "percentile_rank_improvement":66.6666666667
    },
    {
        "user_id":3,
        "activity":"SC",
        "week":2,
        "week_start_date":"2026-02-27",
        "total_peaks":36,
        "total_steps":36,
        "step_time_mean_sec":1.9943250358,
        "step_time_std_sec":0.5895969216,
        "step_time_cv_pct":29.1520229851,
        "total_duration_sec":35.6404464018,
        "num_cycles":36,
        "cycle_time_mean_sec":1.9800248001,
        "cycle_time_std_sec":0.5296626895,
        "cycle_time_cv_pct":26.6573588607,
        "left_peaks":0,
        "right_peaks":0,
        "composite_score":68.9281907357,
        "user_group":"stable",
        "best_activity":"SC",
        "composite_score_norm":0.697180982,
        "step_time_cv_pct_norm":0.3017229353,
        "cycle_time_cv_pct_norm":0.2734158608,
        "total_duration_sec_norm":0.1669955112,
        "total_peaks_norm":0.1181434599,
        "composite_score_overall":51.3495063152,
        "perf_change_pct_SC":0.078671864,
        "perf_change_pct_STS":44.5014775634,
        "perf_change_pct_TUG":3.0539119499,
        "perf_change_pct_W":2.847139799,
        "perf_change_pct_overall":3.6743324329,
        "percentile_rank_absolute":16.6666666667,
        "percentile_rank_improvement":66.6666666667
    },
    {
        "user_id":3,
        "activity":"SC",
        "week":3,
        "week_start_date":"2026-03-06",
        "total_peaks":37,
        "total_steps":37,
        "step_time_mean_sec":1.9102017684,
        "step_time_std_sec":0.5571654446,
        "step_time_cv_pct":28.7857875565,
        "total_duration_sec":33.1527940017,
        "num_cycles":37,
        "cycle_time_mean_sec":1.7909205706,
        "cycle_time_std_sec":0.5135739039,
        "cycle_time_cv_pct":28.5814059855,
        "left_peaks":0,
        "right_peaks":0,
        "composite_score":69.6258754269,
        "user_group":"stable",
        "best_activity":"SC",
        "composite_score_norm":0.704759817,
        "step_time_cv_pct_norm":0.2936903299,
        "cycle_time_cv_pct_norm":0.3078425095,
        "total_duration_sec_norm":0.1471767924,
        "total_peaks_norm":0.1223628692,
        "composite_score_overall":50.0144881956,
        "perf_change_pct_SC":1.0916588079,
        "perf_change_pct_STS":-24.204861686,
        "perf_change_pct_TUG":-1.7177808849,
        "perf_change_pct_W":6.9705433237,
        "perf_change_pct_overall":0.9789391902,
        "percentile_rank_absolute":16.6666666667,
        "percentile_rank_improvement":66.6666666667
    },
    {
        "user_id":3,
        "activity":"SC",
        "week":4,
        "week_start_date":"2026-03-13",
        "total_peaks":38,
        "total_steps":37,
        "step_time_mean_sec":1.9178196575,
        "step_time_std_sec":0.5976821013,
        "step_time_cv_pct":29.5338994069,
        "total_duration_sec":34.9789761624,
        "num_cycles":38,
        "cycle_time_mean_sec":1.8469093292,
        "cycle_time_std_sec":0.439880011,
        "cycle_time_cv_pct":23.8420485866,
        "left_peaks":0,
        "right_peaks":0,
        "composite_score":68.2007096874,
        "user_group":"stable",
        "best_activity":"SC",
        "composite_score_norm":0.6892784741,
        "step_time_cv_pct_norm":0.3100985931,
        "cycle_time_cv_pct_norm":0.2230419919,
        "total_duration_sec_norm":0.1617256862,
        "total_peaks_norm":0.1265822785,
        "composite_score_overall":51.1427140791,
        "perf_change_pct_SC":-0.9775772025,
        "perf_change_pct_STS":-0.6613103463,
        "perf_change_pct_TUG":3.6502644568,
        "perf_change_pct_W":8.2173752361,
        "perf_change_pct_overall":3.2568202001,
        "percentile_rank_absolute":16.6666666667,
        "percentile_rank_improvement":66.6666666667
    },
    {
        "user_id":3,
        "activity":"SC",
        "week":5,
        "week_start_date":"2026-03-20",
        "total_peaks":37,
        "total_steps":36,
        "step_time_mean_sec":2.0157942695,
        "step_time_std_sec":0.5748224351,
        "step_time_cv_pct":29.7677745446,
        "total_duration_sec":34.0978938795,
        "num_cycles":37,
        "cycle_time_mean_sec":1.8446317057,
        "cycle_time_std_sec":0.5767267076,
        "cycle_time_cv_pct":31.2104738459,
        "left_peaks":0,
        "right_peaks":0,
        "composite_score":67.7551735909,
        "user_group":"stable",
        "best_activity":"SC",
        "composite_score_norm":0.6844386882,
        "step_time_cv_pct_norm":0.3152281534,
        "cycle_time_cv_pct_norm":0.3548839745,
        "total_duration_sec_norm":0.1547062482,
        "total_peaks_norm":0.1223628692,
        "composite_score_overall":49.4401911,
        "perf_change_pct_SC":-1.6244629009,
        "perf_change_pct_STS":-24.4555612214,
        "perf_change_pct_TUG":4.1809514746,
        "perf_change_pct_W":0.3923708671,
        "perf_change_pct_overall":-0.1805630577,
        "percentile_rank_absolute":16.6666666667,
        "percentile_rank_improvement":66.6666666667
    },
    {
        "user_id":3,
        "activity":"SC",
        "week":6,
        "week_start_date":"2026-03-27",
        "total_peaks":37,
        "total_steps":38,
        "step_time_mean_sec":1.9483275106,
        "step_time_std_sec":0.5636286347,
        "step_time_cv_pct":29.5784580617,
        "total_duration_sec":32.9498151955,
        "num_cycles":37,
        "cycle_time_mean_sec":1.7837922258,
        "cycle_time_std_sec":0.5219879002,
        "cycle_time_cv_pct":29.3599737252,
        "left_peaks":0,
        "right_peaks":0,
        "composite_score":68.1158246957,
        "user_group":"stable",
        "best_activity":"SC",
        "composite_score_norm":0.6883563823,
        "step_time_cv_pct_norm":0.3110758937,
        "cycle_time_cv_pct_norm":0.3217732899,
        "total_duration_sec_norm":0.1455596936,
        "total_peaks_norm":0.1223628692,
        "composite_score_overall":49.7722660876,
        "perf_change_pct_SC":-1.1008239776,
        "perf_change_pct_STS":-15.1064924207,
        "perf_change_pct_TUG":2.6539721233,
        "perf_change_pct_W":2.2521535689,
        "perf_change_pct_overall":0.4898942674,
        "percentile_rank_absolute":16.6666666667,
        "percentile_rank_improvement":66.6666666667
    },
    {
        "user_id":3,
        "activity":"SC",
        "week":7,
        "week_start_date":"2026-04-03",
        "total_peaks":37,
        "total_steps":37,
        "step_time_mean_sec":1.9976052841,
        "step_time_std_sec":0.5551166506,
        "step_time_cv_pct":28.81208571,
        "total_duration_sec":34.6611512132,
        "num_cycles":37,
        "cycle_time_mean_sec":1.8765284178,
        "cycle_time_std_sec":0.333681175,
        "cycle_time_cv_pct":17.8420312222,
        "left_peaks":0,
        "right_peaks":0,
        "composite_score":69.5757769994,
        "user_group":"stable",
        "best_activity":"SC",
        "composite_score_norm":0.7042156059,
        "step_time_cv_pct_norm":0.2942671247,
        "cycle_time_cv_pct_norm":0.1156846995,
        "total_duration_sec_norm":0.159193627,
        "total_peaks_norm":0.1223628692,
        "composite_score_overall":50.449737845,
        "perf_change_pct_SC":1.0189195696,
        "perf_change_pct_STS":-42.1794454691,
        "perf_change_pct_TUG":1.3476493939,
        "perf_change_pct_W":9.3031891529,
        "perf_change_pct_overall":1.857705513,
        "percentile_rank_absolute":16.6666666667,
        "percentile_rank_improvement":66.6666666667
    },
    {
        "user_id":3,
        "activity":"SC",
        "week":8,
        "week_start_date":"2026-04-10",
        "total_peaks":37,
        "total_steps":38,
        "step_time_mean_sec":1.8395348947,
        "step_time_std_sec":0.5630903464,
        "step_time_cv_pct":28.9998304952,
        "total_duration_sec":33.9704390469,
        "num_cycles":37,
        "cycle_time_mean_sec":1.8389317713,
        "cycle_time_std_sec":0.4209293856,
        "cycle_time_cv_pct":23.1754487712,
        "left_peaks":0,
        "right_peaks":0,
        "composite_score":69.2181200053,
        "user_group":"stable",
        "best_activity":"SC",
        "composite_score_norm":0.7003304364,
        "step_time_cv_pct_norm":0.2983849125,
        "cycle_time_cv_pct_norm":0.2111146345,
        "total_duration_sec_norm":0.1536908364,
        "total_peaks_norm":0.1223628692,
        "composite_score_overall":52.6577960475,
        "perf_change_pct_SC":0.4996278753,
        "perf_change_pct_STS":49.8992343413,
        "perf_change_pct_TUG":5.0104290756,
        "perf_change_pct_W":8.3290681689,
        "perf_change_pct_overall":6.3157612286,
        "percentile_rank_absolute":16.6666666667,
        "percentile_rank_improvement":66.6666666667
    },
    {
        "user_id":3,
        "activity":"SC",
        "week":9,
        "week_start_date":"2026-04-17",
        "total_peaks":37,
        "total_steps":38,
        "step_time_mean_sec":1.9268897856,
        "step_time_std_sec":0.5696863225,
        "step_time_cv_pct":29.3104659668,
        "total_duration_sec":34.560720544,
        "num_cycles":37,
        "cycle_time_mean_sec":1.8702711579,
        "cycle_time_std_sec":0.5089469596,
        "cycle_time_cv_pct":26.9503038549,
        "left_peaks":0,
        "right_peaks":0,
        "composite_score":68.6263541732,
        "user_group":"stable",
        "best_activity":"SC",
        "composite_score_norm":0.6939021807,
        "step_time_cv_pct_norm":0.3051980496,
        "cycle_time_cv_pct_norm":0.2786574759,
        "total_duration_sec_norm":0.1583935123,
        "total_peaks_norm":0.1223628692,
        "composite_score_overall":51.5245392211,
        "perf_change_pct_SC":-0.3595726622,
        "perf_change_pct_STS":45.0332030794,
        "perf_change_pct_TUG":2.164987903,
        "perf_change_pct_W":5.3219564926,
        "perf_change_pct_overall":4.0277227764,
        "percentile_rank_absolute":16.6666666667,
        "percentile_rank_improvement":66.6666666667
    },
    {
        "user_id":3,
        "activity":"SC",
        "week":10,
        "week_start_date":"2026-04-24",
        "total_peaks":36,
        "total_steps":38,
        "step_time_mean_sec":1.8943445583,
        "step_time_std_sec":0.5715960692,
        "step_time_cv_pct":29.72686429,
        "total_duration_sec":33.0636477599,
        "num_cycles":36,
        "cycle_time_mean_sec":1.83686932,
        "cycle_time_std_sec":0.6182994554,
        "cycle_time_cv_pct":33.6146102181,
        "left_peaks":0,
        "right_peaks":0,
        "composite_score":67.8331083184,
        "user_group":"stable",
        "best_activity":"SC",
        "composite_score_norm":0.6852852804,
        "step_time_cv_pct_norm":0.3143308728,
        "cycle_time_cv_pct_norm":0.3979007786,
        "total_duration_sec_norm":0.1464665789,
        "total_peaks_norm":0.1181434599,
        "composite_score_overall":51.2748805785,
        "perf_change_pct_SC":-1.511307399,
        "perf_change_pct_STS":2.2612179979,
        "perf_change_pct_TUG":4.8419798179,
        "perf_change_pct_W":8.1092316512,
        "perf_change_pct_overall":3.5236635368,
        "percentile_rank_absolute":16.6666666667,
        "percentile_rank_improvement":66.6666666667
    },
    {
        "user_id":3,
        "activity":"SC",
        "week":11,
        "week_start_date":"2026-05-01",
        "total_peaks":37,
        "total_steps":37,
        "step_time_mean_sec":1.9086121356,
        "step_time_std_sec":0.537634023,
        "step_time_cv_pct":28.8354198232,
        "total_duration_sec":34.5481003299,
        "num_cycles":37,
        "cycle_time_mean_sec":1.8672744144,
        "cycle_time_std_sec":0.482268257,
        "cycle_time_cv_pct":25.7941874486,
        "left_peaks":0,
        "right_peaks":0,
        "composite_score":69.5313251187,
        "user_group":"stable",
        "best_activity":"SC",
        "composite_score_norm":0.7037327324,
        "step_time_cv_pct_norm":0.2947789095,
        "cycle_time_cv_pct_norm":0.2579712812,
        "total_duration_sec_norm":0.1582929691,
        "total_peaks_norm":0.1223628692,
        "composite_score_overall":50.1055944502,
        "perf_change_pct_SC":0.9543787028,
        "perf_change_pct_STS":-18.9215333804,
        "perf_change_pct_TUG":2.4479394163,
        "perf_change_pct_W":2.840581821,
        "perf_change_pct_overall":1.1628821491,
        "percentile_rank_absolute":16.6666666667,
        "percentile_rank_improvement":66.6666666667
    },
    {
        "user_id":3,
        "activity":"SC",
        "week":12,
        "week_start_date":"2026-05-08",
        "total_peaks":38,
        "total_steps":38,
        "step_time_mean_sec":1.9117830625,
        "step_time_std_sec":0.5843426415,
        "step_time_cv_pct":29.0083749399,
        "total_duration_sec":33.7422402015,
        "num_cycles":38,
        "cycle_time_mean_sec":1.775907379,
        "cycle_time_std_sec":0.4560753439,
        "cycle_time_cv_pct":25.5918342035,
        "left_peaks":0,
        "right_peaks":0,
        "composite_score":69.2018426935,
        "user_group":"stable",
        "best_activity":"SC",
        "composite_score_norm":0.7001536186,
        "step_time_cv_pct_norm":0.2985723169,
        "cycle_time_cv_pct_norm":0.254350609,
        "total_duration_sec_norm":0.1518728136,
        "total_peaks_norm":0.1265822785,
        "composite_score_overall":50.457951678,
        "perf_change_pct_SC":0.4759944138,
        "perf_change_pct_STS":15.1106319541,
        "perf_change_pct_TUG":6.5670024734,
        "perf_change_pct_W":-3.0297189176,
        "perf_change_pct_overall":1.8742891906,
        "percentile_rank_absolute":16.6666666667,
        "percentile_rank_improvement":66.6666666667
    }
]